LICENSE.txt
README.md
setup.py
rocket_ouareth_mohamed.egg-info/PKG-INFO
rocket_ouareth_mohamed.egg-info/SOURCES.txt
rocket_ouareth_mohamed.egg-info/dependency_links.txt
rocket_ouareth_mohamed.egg-info/top_level.txt
rocket_salah_ouareth/__init__.py
rocket_salah_ouareth/rocket.py