Metadata-Version: 2.1
Name: rocket-ouareth-mohamed
Version: 0.1
Summary: A package for simulating rockets and shuttles.
Home-page: https://github.com/yourusername/rocket
Author: ouareth mohamed
Author-email: ms.ouareth@esi-sba.dz
License: MIT
License-File: LICENSE.txt
